stjlib/__init__.py
stjlib/stj.py
stjlib/core/__init__.py
stjlib/core/data_classes.py
stjlib/core/enums.py
stjlib/validation/__init__.py
stjlib/validation/validators.py
stjlib-0.6.4.dist-info/licenses/LICENSE
stjlib-0.6.4.dist-info/METADATA
stjlib-0.6.4.dist-info/WHEEL
stjlib-0.6.4.dist-info/top_level.txt
stjlib-0.6.4.dist-info/RECORD
