Metadata-Version: 2.4
Name: stjlib
Version: 0.6.4
Summary: A Python wrapper for the Standard Transcription JSON (STJ) format.
Home-page: https://github.com/yaniv-golan/stjlib
Author: Yaniv Golan
Author-email: yaniv@golan.name
Project-URL: Bug Tracker, https://github.com/yaniv-golan/stjlib/issues
Classifier: Programming Language :: Python :: 3
Classifier: Programming Language :: Python :: 3.9
Classifier: Programming Language :: Python :: 3.10
Classifier: Programming Language :: Python :: 3.11
Classifier: Programming Language :: Python :: 3.12
Classifier: License :: OSI Approved :: MIT License
Classifier: Operating System :: OS Independent
Requires-Python: >=3.9
License-File: LICENSE
Requires-Dist: iso639-lang>=2.5.0
Requires-Dist: python-dateutil
Dynamic: license-file
